AUTHORS.rst
CONTRIBUTING.rst
HISTORY.rst
LICENSE
MANIFEST.in
README.rst
setup.cfg
setup.py
deploy_py/__init__.py
deploy_py/cli.py
deploy_py/deploy_py.py
deploy_py/exceptions.py
deploy_py.egg-info/PKG-INFO
deploy_py.egg-info/SOURCES.txt
deploy_py.egg-info/dependency_links.txt
deploy_py.egg-info/entry_points.txt
deploy_py.egg-info/not-zip-safe
deploy_py.egg-info/requires.txt
deploy_py.egg-info/top_level.txt
deploy_py/config/__init__.py
deploy_py/config/config.py
deploy_py/config/exceptions.py
deploy_py/docker/__init__.py
deploy_py/docker/docker.py
deploy_py/docker/exceptions.py
deploy_py/helm/__init__.py
deploy_py/helm/exceptions.py
deploy_py/helm/helm.py
deploy_py/helm/port_forwarding.py
deploy_py/helm/storage/__init__.py
deploy_py/helm/storage/artifactory.py
deploy_py/helm/storage/chart_museum.py
deploy_py/helm/storage/exceptions.py
deploy_py/helm/storage/gcs.py
deploy_py/helm/storage/repo.py
deploy_py/kube/__init__.py
deploy_py/kube/exceptions.py
deploy_py/kube/kube.py
deploy_py/logger/__init__.py
docs/Makefile
docs/authors.rst
docs/conf.py
docs/contributing.rst
docs/history.rst
docs/index.rst
docs/installation.rst
docs/make.bat
docs/readme.rst
docs/usage.rst
tests/__init__.py
tests/test_deploy_py.py