Metadata-Version: 1.1
Name: deploy-py
Version: 0.3.0
Summary: Deploy versioned applications with Docker, Helm and Kubernetes.
Home-page: https://github.com/kylie-a/deploy_py
Author: Kylie Auld
Author-email: kylie@kylie-a.wtf
License: MIT license
Keywords: deploy_py
Platform: UNKNOWN
Classifier: Development Status :: 2 - Pre-Alpha
Classifier: Intended Audience :: Developers
Classifier: License :: OSI Approved :: MIT License
Classifier: Natural Language :: English
Classifier: Programming Language :: Python :: 3
Classifier: Programming Language :: Python :: 3.6
Classifier: Programming Language :: Python :: 3.7
